{
   "AlenaActiva": true,
   "CambioActo": false,
   "CollisionableObject": [
      {
         "Texture": 276,
         "h": 206.0,
         "rotation": 0.0,
         "soundEffect": 1,
         "w": 60.0,
         "x": 700.0,
         "y": 260.0
      }
   ],
   "GOTransiciones": [
      {
         "Texture": 29,
         "h": 60.0,
         "rotat": -90.0,
         "rotation": -90.0,
         "scneNum": 25,
         "soundEffect": 1,
         "w": 60.0,
         "x": 235.0,
         "y": 350.0
      },
      {
         "Texture": 29,
         "h": 60.0,
         "rotat": -90.0,
         "rotation": -90.0,
         "scneNum": 27,
         "soundEffect": 1,
         "w": 60.0,
         "x": 522.0,
         "y": 350.0
      }
   ],
   "HeaderActo": "",
   "MusicVolume": [
      0
   ],
   "NPC": [
      {
         "Anims": [
            [
               4,
               5,
               6,
               7
            ]
         ],
         "Texture": 124,
         "animation": true,
         "dialogo": "Ander17",
         "done": false,
         "h": 206.0,
         "heightFrame": 149,
         "loop": true,
         "numColsFrame": 2,
         "numFilsFrame": 4,
         "repeatDialog": true,
         "rotation": 0.0,
         "soundEffect": 1,
         "vel": 200.0,
         "w": 60.0,
         "widthFrame": 41,
         "x": 700.0,
         "y": 260.0
      }
   ],
   "PlayerPos": {
      "x": 235.0,
      "y": 360.0
   },
   "PlayerTam": {
      "h": 201.6,
      "w": 84.0
   },
   "StopActualMusic": [
      false
   ],
   "Texture": 92,
   "actNumber": -1,
   "h": 720.0,
   "rotation": 0.0,
   "soundEffect": 1,
   "w": 1280.0,
   "x": 0.0,
   "y": 0.0
}